[
    {
        "genre": "Action",
        "sales": 1741.02
    },
    {
        "genre": "Adventure",
        "sales": 234.82
    },
    {
        "genre": "Fighting",
        "sales": 444.93
    },
    {
        "genre": "Misc",
        "sales": 799.93
    },
    {
        "genre": "Platform",
        "sales": 829.15
    },
    {
        "genre": "Puzzle",
        "sales": 242.9
    },
    {
        "genre": "Racing",
        "sales": 729.02
    },
    {
        "genre": "Role-Playing",
        "sales": 924.5
    },
    {
        "genre": "Shooter",
        "sales": 1032.37
    },
    {
        "genre": "Simulation",
        "sales": 390.39
    },
    {
        "genre": "Sports",
        "sales": 1325.27
    },
    {
        "genre": "Strategy",
        "sales": 174.11
    }
]